fennecs/discovery/__init__.py
fennecs/inference/__init__.py
fennecs-0.0.0.dist-info/LICENSE
fennecs-0.0.0.dist-info/METADATA
fennecs-0.0.0.dist-info/WHEEL
fennecs-0.0.0.dist-info/RECORD
