Metadata-Version: 2.1
Name: fennecs
Version: 0.0.0
Summary: Efficient causality tools with hypothesis testing
License: Apache-2.0
Author: Diviyan Kalainathan
Requires-Python: >=3.10,<4.0
Classifier: License :: OSI Approved :: Apache Software License
Classifier: Programming Language :: Python :: 3
Classifier: Programming Language :: Python :: 3.10
Classifier: Programming Language :: Python :: 3.11
Requires-Dist: numpy (>=1.26.4,<2.0.0)
